search_content_gcs/__init__.py
search_content_gcs/api.py
search_content_gcs/client.py
search_content_gcs/error.py
search_content_gcs/exception.py
search_content_gcs/models/__init__.py
search_content_gcs/models/gcs_api_key.py
search_content_gcs/models/google_custom_search.py
search_content_gcs/models/simple_youtube_data.py
search_content_gcs/parser/__init__.py
search_content_gcs/utils/__init__.py
search_content_gcs/utils/youtube_url.py
search_content_gcs-0.1.1.dist-info/METADATA
search_content_gcs-0.1.1.dist-info/WHEEL
search_content_gcs-0.1.1.dist-info/RECORD
