Metadata-Version: 2.1
Name: search-content-gcs
Version: 0.1.1
Summary: 
Author: heeya8876
Author-email: heeya8876@gmail.com
Requires-Python: >=3.10,<4.0
Classifier: Programming Language :: Python :: 3
Classifier: Programming Language :: Python :: 3.10
Classifier: Programming Language :: Python :: 3.11
Classifier: Programming Language :: Python :: 3.12
